Metadata-Version: 2.1
Name: pathme-viewer
Version: 0.0.9
Summary: A plugin for PathMe that allows to explore overlaps across pathway databases
Home-page: https://github.com/PathwayMerger/PathMe-Viewer
Author: Daniel Domingo-Fernández
Author-email: daniel.domingo.fernandez@scai.fraunhofer.de
Maintainer: Daniel Domingo-Fernández
Maintainer-email: daniel.domingo.fernandez@scai.fraunhofer.de
License: Apache 2.0 License
Download-URL: https://pypi.org/project/pathme-viewer/
Project-URL: Bug Tracker, https://github.com/PathwayMerger/PathMe-Viewer/issues
Project-URL: Source Code, https://github.com/PathwayMerger/PathMe-Viewer
Project-URL: Documentation, https://pathme-viewer.readthedocs.io/en/latest/
Keywords: Pathway Databases,Systems Biology,Networks Biology,Biological Expression Language
Platform: UNKNOWN
Classifier: Development Status :: 4 - Beta
Classifier: Environment :: Console
Classifier: Intended Audience :: Developers
Classifier: Intended Audience :: Science/Research
Classifier: License :: OSI Approved :: Apache Software License
Classifier: Operating System :: OS Independent
Classifier: Programming Language :: Python
Classifier: Programming Language :: Python :: 3.7
Classifier: Programming Language :: Python :: 3.6
Classifier: Programming Language :: Python :: 3 :: Only
Classifier: Topic :: Scientific/Engineering :: Bio-Informatics
Requires-Python: >=3.6
Provides-Extra: docs
Provides-Extra: web
